app/__init__.py
app/helpers.py
app/main.py
app/py.typed
app/types.py
app/utilities.py
app/routes/__init__.py
app/routes/hf_models.py
app/runners/__init__.py
app/runners/audio_classification.py
app/runners/automatic_speech_recognition.py
app/runners/depth_estimation.py
app/runners/document_question_answering.py
app/runners/feature_extraction.py
app/runners/fill_mask.py
app/runners/image_classification.py
app/runners/image_feature_extraction.py
app/runners/image_segmentation.py
app/runners/image_text_to_text.py
app/runners/image_to_image.py
app/runners/image_to_text.py
app/runners/mask_generation.py
app/runners/object_detection.py
app/runners/question_answering.py
app/runners/sentiment.py
app/runners/summarization.py
app/runners/table_question_answering.py
app/runners/text2text_generation.py
app/runners/text_generation.py
app/runners/text_to_audio.py
app/runners/text_to_image.py
app/runners/text_to_speech.py
app/runners/token_classification.py
app/runners/translation.py
app/runners/video_classification.py
app/runners/visual_question_answering.py
app/runners/zero_shot_audio_classification.py
app/runners/zero_shot_classification.py
app/runners/zero_shot_image_classification.py
app/runners/zero_shot_object_detection.py
app/runners/patches/__init__.py
app/runners/patches/patch_offline_kwarg.py
app/services/__init__.py
app/services/hf_models_service.py
app/static/favicon.ico
app/views/__init__.py
app/views/hf_models_table.py
hf_inference-0.1.0.dist-info/METADATA
hf_inference-0.1.0.dist-info/WHEEL
hf_inference-0.1.0.dist-info/entry_points.txt
hf_inference-0.1.0.dist-info/licenses/LICENSE
hf_inference-0.1.0.dist-info/RECORD
