Metadata-Version: 2.4
Name: hf-inference
Version: 0.1.0
Summary: A unified FastAPI server for Hugging Face model inference across 31+ tasks
Project-URL: Homepage, https://github.com/megazord-studio/hf_inference
Project-URL: Repository, https://github.com/megazord-studio/hf_inference
Project-URL: Issues, https://github.com/megazord-studio/hf_inference/issues
Project-URL: Changelog, https://github.com/megazord-studio/hf_inference/blob/main/CHANGELOG.md
Author-email: "megazord.studio GmbH" <info@megazord.studio>
Maintainer-email: "megazord.studio GmbH" <info@megazord.studio>
License:                     GNU GENERAL PUBLIC LICENSE
License-File: LICENSE
Keywords: ai,diffusers,fastapi,huggingface,inference,ml,transformers
Classifier: Development Status :: 3 - Alpha
Classifier: Framework :: FastAPI
Classifier: Intended Audience :: Developers
Classifier: License :: OSI Approved :: GNU General Public License v3 (GPLv3)
Classifier: Programming Language :: Python
Classifier: Programming Language :: Python :: 3
Classifier: Programming Language :: Python :: 3 :: Only
Classifier: Programming Language :: Python :: 3.12
Classifier: Topic :: Scientific/Engineering :: Artificial Intelligence
Classifier: Topic :: Software Development :: Libraries
Requires-Python: >=3.12
Requires-Dist: accelerate~=1.0
Requires-Dist: av~=16.0
Requires-Dist: diffusers~=0.35
Requires-Dist: einops~=0.8
Requires-Dist: emoji~=2.15
Requires-Dist: fastapi~=0.119
Requires-Dist: huggingface-hub~=0.35
Requires-Dist: numpy<2.0.0,>=1.15.0
Requires-Dist: pandas~=2.3
Requires-Dist: pillow~=11.3
Requires-Dist: protobuf~=6.32
Requires-Dist: pyctcdecode~=0.5
Requires-Dist: pydantic~=2.12
Requires-Dist: pytesseract~=0.3
Requires-Dist: python-multipart~=0.0.20
Requires-Dist: sacremoses~=0.1
Requires-Dist: safetensors~=0.6
Requires-Dist: sentence-transformers~=5.1
Requires-Dist: sentencepiece~=0.2
Requires-Dist: soundfile~=0.13
Requires-Dist: timm~=1.0
Requires-Dist: torchvision~=0.23.0
Requires-Dist: torch~=2.8.0
Requires-Dist: transformers~=4.57
Requires-Dist: uvicorn~=0.37
Provides-Extra: dev
Requires-Dist: bandit; extra == 'dev'
Requires-Dist: httpx; extra == 'dev'
Requires-Dist: mdformat; extra == 'dev'
Requires-Dist: mypy; extra == 'dev'
Requires-Dist: poethepoet; extra == 'dev'
Requires-Dist: pytest; extra == 'dev'
Requires-Dist: pytest-asyncio; extra == 'dev'
Requires-Dist: radon; extra == 'dev'
Requires-Dist: ruff; extra == 'dev'
Requires-Dist: vulture; extra == 'dev'
